XStatic_FileSaver-1.3.2.0-py2.7-nspkg.pth
XStatic_FileSaver-1.3.2.0.dist-info/METADATA
XStatic_FileSaver-1.3.2.0.dist-info/RECORD
XStatic_FileSaver-1.3.2.0.dist-info/WHEEL
XStatic_FileSaver-1.3.2.0.dist-info/namespace_packages.txt
XStatic_FileSaver-1.3.2.0.dist-info/top_level.txt
xstatic/pkg/filesaver/__init__.py
xstatic/pkg/filesaver/data/FileSaver.js
