Metadata-Version: 2.1
Name: XStatic-FileSaver
Version: 1.3.2.0
Summary: FileSaver 1.3.2 (XStatic packaging standard)
Home-page: https://github.com/eligrey/FileSaver.js
Maintainer: xinni.ge
Maintainer-email: xinni.ge@ntt.com
License: MIT
Keywords: filesaver xstatic
Platform: any
